tagmark/__init__.py
tagmark/cli.py
tagmark/condition_example.json
tagmark/core/__init__.py
tagmark/core/convert.py
tagmark/core/data.py
tagmark/core/export.py
tagmark/core/github.py
tagmark/core/log.py
tagmark/core/tag.py
tagmark/tools/autotagdef.py
tagmark/tools/checktag.py
tagmark/tools/convert/__init__.py
tagmark/tools/convert/diigo.py
tagmark/tools/convert/tagmark.py
tagmark/tools/export/__init__.py
tagmark/tools/export/diigo.py
tagmark/tools/maketagdoc.py
tagmark/tools/maketagdoc.toml.default
tagmark-1.0.0.dist-info/METADATA
tagmark-1.0.0.dist-info/WHEEL
tagmark-1.0.0.dist-info/entry_points.txt
tagmark-1.0.0.dist-info/RECORD
