Metadata-Version: 2.1
Name: tagmark
Version: 1.0.0
Summary: TagMark is a tag based bookmark solution for intensive github users. This tool tagmark (python) is the data processing part of TagMark solution.
Author: pwnfan
Author-email: pwnfan@proton.me
Requires-Python: >=3.11,<4.0
Classifier: Programming Language :: Python :: 3
Classifier: Programming Language :: Python :: 3.11
Requires-Dist: click (>=8.1.3,<9.0.0)
Requires-Dist: dacite (>=1.8.1,<2.0.0)
Requires-Dist: fake-useragent (>=1.2.1,<2.0.0)
Requires-Dist: python-dotenv (>=1.0.0,<2.0.0)
Requires-Dist: requests (>=2.31.0,<3.0.0)
Requires-Dist: requests-mock (>=1.11.0,<2.0.0)
Requires-Dist: revchatgpt (>=6.8.6,<7.0.0)
Requires-Dist: structlog (>=23.1.0,<24.0.0)
Requires-Dist: tqdm (>=4.65.0,<5.0.0)
